overlay4u
