Metadata-Version: 1.1
Name: overlay4u
Version: 0.0.4
Summary: overlay4u
Home-page: https://github.com/ravenac95/overlay4u
Author: Reuven V. Gonzales
Author-email: reuven@tobetter.us
License: MIT
Keywords: overlayfs
Platform: Ubuntu
Classifier: License :: OSI Approved :: MIT License
Classifier: Intended Audience :: Developers
Classifier: Programming Language :: Python
Classifier: Operating System :: POSIX
Classifier: Topic :: Software Development :: Build Tools
